LICENSE.md
MANIFEST.in
readme.md
setup.cfg
setup.py
sermon_audio.egg-info/PKG-INFO
sermon_audio.egg-info/SOURCES.txt
sermon_audio.egg-info/dependency_links.txt
sermon_audio.egg-info/not-zip-safe
sermon_audio.egg-info/requires.txt
sermon_audio.egg-info/top_level.txt
sermonaudio/__init__.py
sermonaudio/sermonaudio.py