Metadata-Version: 1.1
Name: sermon-audio
Version: 0.0.8
Summary: A python wrapper to the Sermon Audio API.
Home-page: https://github.com/npardington/sermon-audio-api
Author: Nathaniel Pardington
Author-email: UNKNOWN
License: MIT
Download-URL: https://github.com/npardington/sermon-audio-api/tarball/0.0.8
Platform: UNKNOWN
Classifier: Programming Language :: Python
